api_schemas/__init__.py
api_schemas/base.py
api_schemas/chunk_embeddings.py
api_schemas/classification.py
api_schemas/embedding.py
api_schemas/image.py
api_schemas/multi_embeddings.py
api_schemas/rank.py
api_schemas/training.py
jinaai_api_schemas-0.0.89.dist-info/METADATA
jinaai_api_schemas-0.0.89.dist-info/WHEEL
jinaai_api_schemas-0.0.89.dist-info/top_level.txt
jinaai_api_schemas-0.0.89.dist-info/RECORD
