Metadata-Version: 2.1
Name: jinaai-api-schemas
Version: 0.0.89
Summary: The schemas for the Jina Serving API
Download-URL: https://github.com/jina-ai/embedding-api-schemas/tags
Author: Jina AI
Author-email: hello@jina.ai
License: Proprietary
Project-URL: Source, https://github.com/jina-ai/embedding-api-schemas.fit/
Project-URL: Tracker, https://github.com/jina-ai/embedding-api-schemas/issues
Classifier: Development Status :: 5 - Production/Stable
Classifier: Intended Audience :: Developers
Classifier: Intended Audience :: Education
Classifier: Intended Audience :: Science/Research
Classifier: Programming Language :: Python :: 3.8
Classifier: Programming Language :: Python :: 3.9
Classifier: Programming Language :: Python :: 3.10
Classifier: Environment :: Console
Classifier: Operating System :: OS Independent
Classifier: Topic :: Scientific/Engineering :: Artificial Intelligence
Requires-Python: >=3.8.0
Requires-Dist: pydantic==1.10.10
Requires-Dist: docarray==0.39.0
